odoo/addons/shopinvader_delivery_instruction/__init__.py
odoo/addons/shopinvader_delivery_instruction/__manifest__.py
odoo/addons/shopinvader_delivery_instruction/i18n/shopinvader_delivery_instruction.pot
odoo/addons/shopinvader_delivery_instruction/services/__init__.py
odoo/addons/shopinvader_delivery_instruction/services/abstract_sale.py
odoo/addons/shopinvader_delivery_instruction/services/cart.py
odoo/addons/shopinvader_delivery_instruction/tests/__init__.py
odoo/addons/shopinvader_delivery_instruction/tests/test_sale_order_picking_note.py
odoo13_addon_shopinvader_delivery_instruction-13.0.1.0.1.dev1.dist-info/METADATA
odoo13_addon_shopinvader_delivery_instruction-13.0.1.0.1.dev1.dist-info/WHEEL
odoo13_addon_shopinvader_delivery_instruction-13.0.1.0.1.dev1.dist-info/top_level.txt
odoo13_addon_shopinvader_delivery_instruction-13.0.1.0.1.dev1.dist-info/RECORD
